Metadata-Version: 2.4
Name: kneaddata
Version: 0.12.3
Home-page: http://huttenhower.sph.harvard.edu/kneaddata
Author: KneadData Development Team
Author-email: kneaddata-users@googlegroups.com
License: MIT
Keywords: microbial,microbiome,bioinformatics,microbiology,metagenomic,metatranscriptomic,kneaddata
Platform: Linux
Platform: MacOS
Classifier: Programming Language :: Python
Classifier: Development Status :: 4 - Beta
Classifier: Environment :: Console
Classifier: Operating System :: MacOS
Classifier: Operating System :: Unix
Classifier: Programming Language :: Python :: 2.7
Classifier: Programming Language :: Python :: 3.4
Classifier: Topic :: Scientific/Engineering :: Bio-Informatics
License-File: LICENSE
Dynamic: author
Dynamic: author-email
Dynamic: classifier
Dynamic: description
Dynamic: home-page
Dynamic: keywords
Dynamic: license
Dynamic: license-file
Dynamic: platform
